bslib/__init__.py
bslib/_version.py
bslib/bslib.py
bslib/bslib_database.csv
bslib-0.7.dist-info/LICENSE
bslib-0.7.dist-info/METADATA
bslib-0.7.dist-info/WHEEL
bslib-0.7.dist-info/top_level.txt
bslib-0.7.dist-info/RECORD
